{
  "name": "Form",
  "description": "A form component for collecting user input with validation and submission handling.",
  "properties": [
    { "name": "id", "type": "string", "description": "Unique identifier" },
    { "name": "fields", "type": "array", "description": "Array of form field configurations" },
    { "name": "submitText", "type": "string", "description": "Submit button text", "defaultValue": "Submit" },
    { "name": "disabled", "type": "boolean", "description": "Whether form is disabled", "defaultValue": false },
    { "name": "className", "type": "string", "description": "CSS class name" }
  ],
  "events": [
    { "name": "onSubmit", "description": "Event fired when form is submitted" },
    { "name": "onChange", "description": "Event fired when any field value changes" }
  ]
}